5th Semester/coa_lab/practice/d_flipflop.v
module d_flipflop(D, C, Q, Q_);
	input D, C;
	output Q, Q_;
	wire nD, e, f;

	not n1(nD, D);
	nand a1(e, D, C);
	nand a2(f, nD, C);
	nand a3(Q, Q_, e);
	nand a4(Q_, Q, f);
endmodule

5th Semester/coa_lab/practice/d_flipflopTB.v
module d_flipflop_tb;

  reg D, C;
  wire Q, Q_;

  d_flipflop dut(D, C, Q, Q_);

  initial begin
		$display("D	C	Q	Q_");

    D = 0;    C = 0;
    #10;
		$display("%b	%b	%b	%b", D, C, Q, Q_);
    C = 1;
    #10;
    C = 0;

    #10;
    D = 1;
    C = 1;
		$display("%b	%b	%b	%b", D, C, Q, Q_);
    #10;
    C = 0;

    D = 0;
    C = 0;
		$display("%b	%b	%b	%b", D, C, Q, Q_);

    #10;
    C = 1;
    #10;
    C = 0;

    #10;
    D = 1;
    C = 1;
    #10;
    C = 0;

    D = 0;
    C = 0;

    #10;
    C = 1;
    #10;
    C = 0;

    #10;
    D = 1;
    C = 1;
    #10;
    C = 0;

    D = 0;
    C = 0;

    #10;
    C = 1;
    #10;
    C = 0;

    #10;
    D = 1;
    C = 1;
    #10;
    C = 0;

    D = 0;
    C = 0;

    #10;
    C = 1;
    #10;
    C = 0;

    #10;
    D = 1;
    C = 1;
    #10;
    C = 0;

    D = 0;
    C = 0;

    #10;
    C = 1;
    #10;
    C = 0;

    #10;
    D = 1;
    C = 1;
    #10;
    C = 0;

    D = 0;
    C = 0;

    #10;
    C = 1;
    #10;
    C = 0;

    #10;
    D = 1;
    C = 1;
    #10;
    C = 0;

    D = 0;
    C = 0;

    #10;
    C = 1;
    #10;
    C = 0;

    #10;
    D = 1;
    C = 1;
    #10;
    C = 0;

  end

endmodule

5th Semester/coa_lab/practice/d_flipflop_tb.vcd
$date
	Wed Dec 20 12:15:39 2023
$end
$version
	ModelSim Version 10.5b
$end
$timescale
	1ps
$end

$scope module d_flipflop_tb $end
$var reg 1 ! D $end
$var reg 1 " C $end
$var wire 1 # Q $end
$var wire 1 $ Q_ $end

$scope module dut $end
$var wire 1 % D $end
$var wire 1 & C $end
$var wire 1 # Q $end
$var wire 1 $ Q_ $end
$var wire 1 ' nD $end
$var wire 1 ( e $end
$var wire 1 ) f $end
$upscope $end
$upscope $end
$enddefinitions $end
#0
$dumpvars
0!
0"
x#
x$
1'
1(
1)
0&
0%
$end
#10
1"
1&
0)
1$
0#
#20
0"
0&
1)
#30
1!
1"
1%
1&
0(
0'
0)
1#
1)
0$
#40
0"
0!
0&
0%
1(
1'
#50
1"
1&
0)
1$
0#
#60
0"
0&
1)
#70
1!
1"
1%
1&
0(
0'
0)
1#
1)
0$
#80
0"
0!
0&
0%
1(
1'
#90
1"
1&
0)
1$
0#
#100
0"
0&
1)
#110
1!
1"
1%
1&
0(
0'
0)
1#
1)
0$
#120
0"
0!
0&
0%
1(
1'
#130
1"
1&
0)
1$
0#
#140
0"
0&
1)
#150
1!
1"
1%
1&
0(
0'
0)
1#
1)
0$
#160
0"
0!
0&
0%
1(
1'
#170
1"
1&
0)
1$
0#
#180
0"
0&
1)
#190
1!
1"
1%
1&
0(
0'
0)
1#
1)
0$
#200
0"
0!
0&
0%
1(
1'
#210
1"
1&
0)
1$
0#
#220
0"
0&
1)
#230
1!
1"
1%
1&
0(
0'
0)
1#
1)
0$
#240
0"
0!
0&
0%
1(
1'
#250
1"
1&
0)
1$
0#
